kinesis_logs_reader/__init__.py
kinesis_logs_reader/__main__.py
kinesis_logs_reader/kinesis_logs_reader.py
kinesis_logs_reader/utils.py
kinesis_logs_reader-0.1.0.dist-info/DESCRIPTION.rst
kinesis_logs_reader-0.1.0.dist-info/METADATA
kinesis_logs_reader-0.1.0.dist-info/RECORD
kinesis_logs_reader-0.1.0.dist-info/WHEEL
kinesis_logs_reader-0.1.0.dist-info/entry_points.txt
kinesis_logs_reader-0.1.0.dist-info/metadata.json
kinesis_logs_reader-0.1.0.dist-info/top_level.txt
tests/__init__.py
tests/test_kinesis_logs_reader.py
