Metadata-Version: 2.0
Name: kinesis-logs-reader
Version: 0.1.0
Summary: Reader for AWS CloudWatch Logs stored in AWS Kinesis
Home-page: https://github.com/obsrvbl/kinesis-logs-reader
Author: Observable Networks
Author-email: support@observable.net
License: Apache
Platform: UNKNOWN
Classifier: Intended Audience :: Developers
Classifier: Intended Audience :: Information Technology
Classifier: Intended Audience :: System Administrators
Classifier: License :: OSI Approved :: Apache Software License
Classifier: Programming Language :: Python :: 2.7
Classifier: Programming Language :: Python :: 3
Classifier: Programming Language :: Python :: 3.4
Classifier: Programming Language :: Python :: 3.5
Requires-Dist: boto3 (>=1.3.1)
Requires-Dist: botocore (>=1.4.19)
